[
  {
    "trendingCategory": "Trending in Politics",
    "trendingTitle": "Annamalai",
    "trendingText": "80700"
  },
  {
    "trendingCategory": "Trending in News",
    "trendingTitle": "Gaza and Lebanon",
    "trendingText": "12000"
  },
  {
    "trendingCategory": "Technology . Trending",
    "trendingTitle": "#galaxyM34giveaway",
    "trendingText": "7551"
  },
  {
    "trendingCategory": "Trending in News",
    "trendingTitle": "#GazaGenocide",
    "trendingText": "20000"
  },
  {
    "trendingCategory": "Trending",
    "trendingTitle": "Leyen",
    "trendingText": "21800"
  },
  {
    "trendingCategory": "Trending",
    "trendingTitle": "Spot ETF",
    "trendingText": "6510"
  },
  {
    "trendingCategory": "Business & finance . Trending",
    "trendingTitle": "#StockMarket",
    "trendingText": "6807"
  }
]
